SajadCrypto/__init__.py
SajodeCrypto-1.dist-info/METADATA
SajodeCrypto-1.dist-info/WHEEL
SajodeCrypto-1.dist-info/top_level.txt
SajodeCrypto-1.dist-info/RECORD
