Metadata-Version: 2.1
Name: SajodeCrypto
Version: 1
Summary: an encryption library for sajad
Author: SajodeCrypto
Classifier: Programming Language :: Python :: 3
